Metadata-Version: 2.1
Name: warpctc-pytorch10-cuda92
Version: 0.1.3
Summary: Pytorch Bindings for warp-ctc maintained by ESPnet
Home-page: https://github.com/espnet/warp-ctc
Author: Jared Casper,Sean Naren,Shinji Watanabe,Jiro Nishitoba,Yusuke Nishioka
Author-email: jared.casper@baidu.com,sean.narenthiran@digitalreasoning.com,sw005320@gmail.com,j.nshtb+github@gmail.com,yusuke.nishioka.0713@gmail.com
License: Apache
Platform: UNKNOWN
